fir.v
`timescale 1ns/1ns

module fir(
    x, h0, h1, h2, h3, y, rst, clk
);

input wire [3:0] x;
input wire [3:0] h0, h1, h2, h3;
input wire rst, clk;

output wire [9:0] y;

reg [3:0] x0, x1, x2, x3;

always @(posedge clk) begin
    if (rst) begin
        x0 <= 4'd0;
        x1 <= 4'd0;
        x2 <= 4'd0;
        x3 <= 4'd0;
    end
    else begin
        x0 <= x;
        x1 <= x0;
        x2 <= x1;
        x3 <= x2;
    end
end

assign y = (h0 * x0) + (h1 * x1) + (h2 * x2) + (h3 * x3);

endmodule

fir_tb.v
module fir_tb;

reg [3:0] x;
reg [3:0] h0, h1, h2, h3;
reg rst, clk;

wire [9:0] y;

fir f1(x,h0,h1,h2,h3,y,rst,clk);

initial begin
    clk = 0;
    forever #50 clk = ~clk;
end

initial begin
    $dumpfile("fir.vcd");
    $dumpvars(0, fir_tb);

    h0 = 4'd1;
    h1 = 4'd2;
    h2 = 4'd2;
    h3 = 4'd1;

    rst = 1;
    x = 4'd0;

    #100;
    rst = 0;

    #25 x = 4'd1;
    #100 x = 4'd2;
    #100 x = 4'd3;
    #100 x = 4'd4;

    #200;
    $finish;
end

initial begin
    $monitor("Time=%0t | rst=%b | x=%d | y=%d",
             $time, rst, x, y);
end

endmodule

simulation/fir.vcd
$date
	Sun Sep 13 21:37:23 2026
$end
$version
	Icarus Verilog
$end
$timescale
	1ns
$end
$scope module fir_tb $end
$var wire 10 ! y [9:0] $end
$var reg 1 " clk $end
$var reg 4 # h0 [3:0] $end
$var reg 4 $ h1 [3:0] $end
$var reg 4 % h2 [3:0] $end
$var reg 4 & h3 [3:0] $end
$var reg 1 ' rst $end
$var reg 4 ( x [3:0] $end
$scope module f1 $end
$var wire 1 " clk $end
$var wire 4 ) h0 [3:0] $end
$var wire 4 * h1 [3:0] $end
$var wire 4 + h2 [3:0] $end
$var wire 4 , h3 [3:0] $end
$var wire 1 ' rst $end
$var wire 4 - x [3:0] $end
$var wire 10 . y [9:0] $end
$var reg 4 / x0 [3:0] $end
$var reg 4 0 x1 [3:0] $end
$var reg 4 1 x2 [3:0] $end
$var reg 4 2 x3 [3:0] $end
$upscope $end
$upscope $end
$enddefinitions $end
$comment Show the parameter values. $end
$dumpall
$end
#0
$dumpvars
bx 2
bx 1
bx 0
bx /
bx .
b0 -
b1 ,
b10 +
b10 *
b1 )
b0 (
1'
b1 &
b10 %
b10 $
b1 #
0"
bx !
$end
#50
b0 !
b0 .
b0 2
b0 1
b0 0
b0 /
1"
#100
0"
0'
#125
b1 (
b1 -
#150
b1 !
b1 .
b1 /
1"
#200
0"
#225
b10 (
b10 -
#250
b100 !
b100 .
b1 0
b10 /
1"
#300
0"
#325
b11 (
b11 -
#350
b1001 !
b1001 .
b1 1
b10 0
b11 /
1"
#400
0"
#425
b100 (
b100 -
#450
b1111 !
b1111 .
b1 2
b10 1
b11 0
b100 /
1"
#500
0"
#550
b10100 !
b10100 .
b10 2
b11 1
b100 0
1"
